LICENSE.md
MANIFEST.in
README.md
setup.py
django_rested.egg-info/PKG-INFO
django_rested.egg-info/SOURCES.txt
django_rested.egg-info/dependency_links.txt
django_rested.egg-info/entry_points.txt
django_rested.egg-info/requires.txt
django_rested.egg-info/top_level.txt
rested/__init__.py
rested/authorize.py
rested/cli.py
rested/errors.py
rested/json.py
rested/models.py
rested/path.py
rested/patterns.py
rested/version.txt
rested/worker.py
rested/commands/__init__.py
rested/commands/command.py
rested/commands/create.py
rested/commands/manage.py
rested/commands/serve.py
rested/commands/shell.py
rested/commands/test.py
rested/commands/version.py
rested/commands/worker.py
rested/middleware/__init__.py
rested/middleware/rest.py
rested/middleware/token.py
rested/signals/__init__.py
rested/signals/consumer.py
rested/signals/patterns.py
rested/signals/utils.py
rested/templates/default/asgi.py
rested/templates/default/settings.py
rested/templates/default/api/__init__.py
rested/templates/default/api/consumers.py
rested/templates/default/api/models.py
rested/templates/default/api/tasks.py
rested/templates/default/api/urls.py
rested/templates/default/api/views.py
rested/templates/default/api/migrations/0001_initial.py
rested/templates/default/api/migrations/0002_auto_20200119_0459.py
rested/templates/default/api/migrations/__init__.py
rested/templates/default/api/static/index.html
rested/templates/default/tests/__init__.py
rested/templates/default/tests/test_broken.py
rested/templates/default/tests/test_client.py
rested/templates/default/tests/test_marker.py
rested/templates/default/tests/test_pt.py
rested/templates/default/tests/test_views.py
rested/test/__init__.py
rested/test/fixtures.py
rested/test/plugin.py
rested/test/rest_client.py
rested/test/rest_test_case.py
rested/validation/__init__.py
rested/validation/utils.py
rested/validation/validation.py
rested/validation/acceptors/__init__.py
rested/validation/acceptors/any.py
rested/validation/acceptors/null.py
rested/validation/acceptors/undefined.py
rested/validation/converters/__init__.py
rested/validation/converters/boolean.py
rested/validation/converters/integer.py
rested/validation/converters/json.py
rested/validation/converters/model.py
