Metadata-Version: 2.1
Name: django-rested
Version: 0.0.15
Summary: Make creating rest APIs in Django simple.
Home-page: https://github.com/mochi-ai/rested.git
Author: Stephen Quebe
Author-email: stephen@mochi.ai
License: UNKNOWN
Platform: UNKNOWN
